[
  {
    "id": 1,
    "name": "Cllr Vanessa Alexander",
    "ward": "Altham",
    "party": "Labour",
    "party_color": "#DC241F",
    "email": "vanessa.alexander@hyndburnbc.gov.uk",
    "phone": "07718 382825",
    "roles": ["Cabinet Portfolio Holder for Resources and Council Operations", "Chair of Learning and Development Panel"]
  },
  {
    "id": 2,
    "name": "Cllr Stephen Button",
    "ward": "Altham",
    "party": "Labour",
    "party_color": "#DC241F",
    "email": "stephen.button@hyndburnbc.gov.uk",
    "phone": "07960 717477",
    "roles": ["Chair of Communities and Wellbeing Overview and Scrutiny Committee", "Vice Chair of Planning (Trees) Sub-Committee"]
  },
  {
    "id": 3,
    "name": "Cllr Mike Booth",
    "ward": "Barnfield",
    "party": "Labour",
    "party_color": "#DC241F",
    "email": "mike.booth@hyndburnbc.gov.uk",
    "phone": "07801 313991",
    "roles": ["Chair of Planning (Trees) Sub-Committee", "Vice Chair of Special Scrutiny Committee"]
  },
  {
    "id": 4,
    "name": "Cllr Clare McKenna",
    "ward": "Barnfield",
    "party": "Labour",
    "party_color": "#DC241F",
    "email": "clare.mckenna@hyndburnbc.gov.uk",
    "phone": "07791 296019",
    "roles": []
  },
  {
    "id": 5,
    "name": "Cllr David James Heap",
    "ward": "Baxenden",
    "party": "Conservative",
    "party_color": "#0087DC",
    "email": "david.heap@hyndburnbc.gov.uk",
    "phone": "07730 196150",
    "roles": []
  },
  {
    "id": 6,
    "name": "Cllr Kath Pratt",
    "ward": "Baxenden",
    "party": "Conservative",
    "party_color": "#0087DC",
    "email": "kathleen.pratt@hyndburnbc.gov.uk",
    "phone": "01254 231794",
    "roles": ["Deputy Leader of the Conservative Group"]
  },
  {
    "id": 7,
    "name": "Cllr Shabir Fazal OBE",
    "ward": "Central",
    "party": "Green Party",
    "party_color": "#6AB023",
    "email": "shabir.fazal@hyndburnbc.gov.uk",
    "phone": null,
    "roles": []
  },
  {
    "id": 8,
    "name": "Cllr Mohammed Younis",
    "ward": "Central",
    "party": "Conservative",
    "party_color": "#0087DC",
    "email": "mohammed.younis@hyndburnbc.gov.uk",
    "phone": "07931 584769",
    "roles": []
  },
  {
    "id": 9,
    "name": "Cllr Loraine Cox",
    "ward": "Church",
    "party": "Conservative",
    "party_color": "#0087DC",
    "email": "loraine.cox@hyndburnbc.gov.uk",
    "phone": "01254 726379",
    "roles": []
  },
  {
    "id": 10,
    "name": "Cllr Stewart Eaves",
    "ward": "Church",
    "party": "Labour",
    "party_color": "#DC241F",
    "email": "stewart.eaves@hyndburnbc.gov.uk",
    "phone": "07877 624066",
    "roles": ["Cabinet Portfolio Holder for Environmental Services", "Chair of Cabinet Committee (Scrap Metal Dealers Act 2013)", "Chair of Cabinet Waste and Recycling Group"]
  },
  {
    "id": 11,
    "name": "Cllr Peter Edwards",
    "ward": "Clayton-le-Moors",
    "party": "Conservative",
    "party_color": "#0087DC",
    "email": "peter.edwards@hyndburnbc.gov.uk",
    "phone": "07955 917038",
    "roles": []
  },
  {
    "id": 12,
    "name": "Cllr Melissa Fisher",
    "ward": "Clayton-le-Moors",
    "party": "Labour & Co-operative",
    "party_color": "#DC241F",
    "email": "melissa.fisher@hyndburnbc.gov.uk",
    "phone": "07976 412160",
    "roles": ["Deputy Leader of the Council", "Cabinet Portfolio Holder for Housing and Communities", "Vice Chair of Judicial Committee (Private Hire and Hackney Carriage Licensing)"]
  },
  {
    "id": 13,
    "name": "Cllr Danny Cassidy",
    "ward": "Huncoat",
    "party": "Conservative",
    "party_color": "#0087DC",
    "email": "danny.cassidy@hyndburnbc.gov.uk",
    "phone": "01254 943180",
    "roles": ["Deputy Leader of the Conservative Group"]
  },
  {
    "id": 14,
    "name": "Cllr Dave Parkins",
    "ward": "Huncoat",
    "party": "Labour",
    "party_color": "#DC241F",
    "email": "dave.parkins@hyndburnbc.gov.uk",
    "phone": "07835 392133",
    "roles": ["Chair of Planning Committee"]
  },
  {
    "id": 15,
    "name": "Cllr Judith Addison",
    "ward": "Immanuel",
    "party": "Conservative",
    "party_color": "#0087DC",
    "email": "judith.addison@hyndburnbc.gov.uk",
    "phone": "07891 018527",
    "roles": []
  },
  {
    "id": 16,
    "name": "Cllr Josh Allen",
    "ward": "Immanuel",
    "party": "Conservative",
    "party_color": "#0087DC",
    "email": "josh.allen@hyndburnbc.gov.uk",
    "phone": "07830 005065",
    "roles": ["Mayor of Hyndburn"]
  },
  {
    "id": 17,
    "name": "Cllr Andrew Clegg",
    "ward": "Milnshaw",
    "party": "Labour",
    "party_color": "#DC241F",
    "email": "andrew.clegg@hyndburnbc.gov.uk",
    "phone": null,
    "roles": []
  },
  {
    "id": 18,
    "name": "Cllr Paul Cox",
    "ward": "Milnshaw",
    "party": "Labour",
    "party_color": "#DC241F",
    "email": "paul.cox@hyndburnbc.gov.uk",
    "phone": "01254 726379",
    "roles": ["Vice Chair of Resources Overview and Scrutiny Committee"]
  },
  {
    "id": 19,
    "name": "Cllr Noordad Aziz",
    "ward": "Netherton",
    "party": "Labour & Co-operative",
    "party_color": "#DC241F",
    "email": "noordad.aziz@hyndburnbc.gov.uk",
    "phone": "07983 641125",
    "roles": ["Deputy Mayor", "Cabinet Portfolio Holder for Transformation, Education and Skills", "Chair of Resources Overview and Scrutiny Committee", "Chair of Standards Committee", "Vice Chair of Audit Committee"]
  },
  {
    "id": 20,
    "name": "Cllr Jodi Clements",
    "ward": "Netherton",
    "party": "Labour & Co-operative",
    "party_color": "#DC241F",
    "email": "jodi.clements@hyndburnbc.gov.uk",
    "phone": null,
    "roles": ["Vice Chair of Communities and Wellbeing Overview and Scrutiny Committee"]
  },
  {
    "id": 21,
    "name": "Cllr Heather Anderson",
    "ward": "Overton",
    "party": "Labour",
    "party_color": "#DC241F",
    "email": "heather.anderson@hyndburnbc.gov.uk",
    "phone": "07913 231750",
    "roles": []
  },
  {
    "id": 22,
    "name": "Cllr Scott Brerton",
    "ward": "Overton",
    "party": "Labour",
    "party_color": "#DC241F",
    "email": "scott.brerton@hyndburnbc.gov.uk",
    "phone": "07851 036095",
    "roles": ["Cabinet Portfolio Holder for Business and Growth", "Chair of Cabinet Committee (Street Naming)"]
  },
  {
    "id": 23,
    "name": "Cllr Clare Yates",
    "ward": "Overton",
    "party": "Labour",
    "party_color": "#DC241F",
    "email": "clare.yates@hyndburnbc.gov.uk",
    "phone": "07722 277094",
    "roles": ["Chair of Licensing Committee", "Vice Chair of Standards Committee"]
  },
  {
    "id": 24,
    "name": "Cllr Joyce Plummer",
    "ward": "Peel",
    "party": "Conservative",
    "party_color": "#0087DC",
    "email": "joyce.plummer@hyndburnbc.gov.uk",
    "phone": "01254 395134",
    "roles": []
  },
  {
    "id": 25,
    "name": "Cllr Clare Pritchard",
    "ward": "Peel",
    "party": "Labour",
    "party_color": "#DC241F",
    "email": "clare.pritchard@hyndburnbc.gov.uk",
    "phone": "07850 928485",
    "roles": ["Cabinet Member"]
  },
  {
    "id": 26,
    "name": "Cllr Bernard Dawson MBE",
    "ward": "Rishton",
    "party": "Labour & Co-operative",
    "party_color": "#DC241F",
    "email": "bernard.dawson@hyndburnbc.gov.uk",
    "phone": "07717 135417",
    "roles": ["Chair of Audit Committee", "Vice Chair of Planning Committee"]
  },
  {
    "id": 27,
    "name": "Cllr Ethan Rawcliffe",
    "ward": "Rishton",
    "party": "Labour",
    "party_color": "#DC241F",
    "email": "ethan.rawcliffe@hyndburnbc.gov.uk",
    "phone": null,
    "roles": ["Cabinet Member", "Vice Chair of Licensing Committee"]
  },
  {
    "id": 28,
    "name": "Cllr Kate Walsh",
    "ward": "Rishton",
    "party": "Labour & Co-operative",
    "party_color": "#DC241F",
    "email": "kate.walsh@hyndburnbc.gov.uk",
    "phone": "07495 138542",
    "roles": ["Cabinet Portfolio Holder for Sustainability and Families", "Chair of Special Scrutiny Committee"]
  },
  {
    "id": 29,
    "name": "Cllr Munsif Dad BEM JP",
    "ward": "Spring Hill",
    "party": "Labour",
    "party_color": "#DC241F",
    "email": "munsif.dad@hyndburnbc.gov.uk",
    "phone": "07506 610753",
    "roles": ["Leader of the Council", "Leader of the Labour Group", "Chair of the Cabinet", "Chair of Leader's Policy Development Board", "Chair of Management Review Committee"]
  },
  {
    "id": 30,
    "name": "Cllr Kimberley Whitehead",
    "ward": "Spring Hill",
    "party": "Labour & Co-operative",
    "party_color": "#DC241F",
    "email": "kimberley.whitehead@hyndburnbc.gov.uk",
    "phone": "07715 304773",
    "roles": ["Deputy Leader of the Council", "Cabinet Portfolio Holder for Culture, Heritage and Arts", "Chair of Judicial Committee (Private Hire and Hackney Carriage Licensing)", "Vice Chair of Management Review Committee"]
  },
  {
    "id": 31,
    "name": "Cllr Andy Gilbert",
    "ward": "St. Andrews",
    "party": "Labour",
    "party_color": "#DC241F",
    "email": "andrew.gilbert@hyndburnbc.gov.uk",
    "phone": "07902 033353",
    "roles": []
  },
  {
    "id": 32,
    "name": "Cllr Steven Smithson",
    "ward": "St. Andrews",
    "party": "Conservative",
    "party_color": "#0087DC",
    "email": "steven.smithson@hyndburnbc.gov.uk",
    "phone": "07541 879451",
    "roles": []
  },
  {
    "id": 33,
    "name": "Cllr Zak Khan",
    "ward": "St. Oswalds",
    "party": "Conservative",
    "party_color": "#0087DC",
    "email": "zak.khan@hyndburnbc.gov.uk",
    "phone": "07513 162129",
    "roles": ["Leader of the Conservative Group"]
  },
  {
    "id": 34,
    "name": "Cllr Tina Walker",
    "ward": "St. Oswalds",
    "party": "Conservative",
    "party_color": "#0087DC",
    "email": "tina.walker@hyndburnbc.gov.uk",
    "phone": "07969 379257",
    "roles": []
  }
]
