[
  {
    "id": "spending-overview",
    "date": "2026-02-15",
    "category": "Analysis",
    "title": "Wyre Borough Council: £678 Million and Lancashire's Narrowest Supplier Base",
    "summary": "51,092 transactions to just 1,558 suppliers — the smallest supplier pool in Lancashire. Lancashire CC receives 48% of all Wyre's spend, driving an HHI of 2,796.8 that classifies as highly concentrated.",
    "image": "/images/articles/finance.jpg",
    "author": "Wyre Council Transparency",
    "tags": ["overview", "spending", "district"]
  },
  {
    "id": "doge-investigation-wyre",
    "date": "2026-02-15",
    "category": "Investigation",
    "title": "Wyre's Concentration Crisis: When 48% Goes to One Place",
    "summary": "Wyre has the most concentrated spending profile in Lancashire with an HHI of 2,796.8. Lancashire County Council receives nearly half of all recorded expenditure, and just 1,558 suppliers handle £678 million across nine years.",
    "image": "/images/articles/magnifying-glass.jpg",
    "author": "Wyre Council Transparency",
    "tags": ["DOGE", "investigation", "concentration"]
  }
]
